lamper_cli/__init__.py
lamper_cli/cli.py
lamper_cli/lamper.py
lamper_cli-0.2.2.dist-info/entry_points.txt
lamper_cli-0.2.2.dist-info/WHEEL
lamper_cli-0.2.2.dist-info/METADATA
lamper_cli-0.2.2.dist-info/RECORD
